[
  {
    "site": "https://k-health365.com",
    "fixed_count": 0,
    "fixed": []
  },
  {
    "site": "https://koreamedicaltour.com",
    "fixed_count": 7,
    "fixed": [
      {
        "id": 978,
        "old": "Navigating Your Health Journey: Unlocking Busan Medical Tour",
        "keyword_used": "Busan medical tourism benefits",
        "new": "Busan medical tourism benefits 101: What First-Timers Should Know",
        "status": 200
      },
      {
        "id": 977,
        "old": "Busan Medical Tourism Benefits: Unlocking World-Class Health",
        "keyword_used": "Busan medical tourism benefits",
        "new": "Behind the Scenes: What Busan medical tourism benefits Actually Involves",
        "status": 200
      },
      {
        "id": 976,
        "old": "Unlock Your Dream Look: Daegu Plastic Surgery Subsidy – Your",
        "keyword_used": "Daegu plastic surgery subsidy",
        "new": "Study Reveals: 8 in 10 People Misunderstand Daegu plastic surgery subsidy",
        "status": 200
      },
      {
        "id": 972,
        "old": "Unveiling the Real Value: Cancer Treatment Cost Korea Insigh",
        "keyword_used": "cancer treatment cost Korea",
        "new": "cancer treatment cost Korea vs What You Think You Know: Key Differences",
        "status": 200
      },
      {
        "id": 637,
        "old": "Don&#8217;t Waste Money: Unlocking the Best Tattoo Removal K",
        "keyword_used": "tattoo removal Korea price",
        "new": "The Real Cost of tattoo removal Korea price — What to Expect",
        "status": 200
      },
      {
        "id": 636,
        "old": "Stop Overpaying for Braces: Unlocking the True Value of Orth",
        "keyword_used": "orthodontics cost Korea",
        "new": "Why Does orthodontics cost Korea Cause Problems? Experts Explain",
        "status": 200
      },
      {
        "id": 410,
        "old": "Korea Skin Whitening: Top 7 Treatments to Unlock Your Glow",
        "keyword_used": "Korea Skin Whitening Top 7 Treatments to Glow",
        "new": "How to Actually Handle Korea Skin Whitening Top 7 Treatments to Glow: A Specialist's Guide",
        "status": 200
      }
    ]
  },
  {
    "site": "https://koreainvest365.com",
    "fixed_count": 1,
    "fixed": [
      {
        "id": 2746,
        "old": "Unlocking Global Opportunities: A Deep Dive into Korean Pens",
        "keyword_used": "Korean pension fund investment",
        "new": "Korean pension fund investment: Frequently Overlooked Facts",
        "status": 200
      }
    ]
  },
  {
    "site": "https://ki-korea.com",
    "fixed_count": 0,
    "fixed": []
  },
  {
    "site": "https://koreainsurance365.com",
    "fixed_count": 0,
    "fixed": []
  },
  {
    "site": "https://kfinance365.com",
    "fixed_count": 0,
    "fixed": []
  },
  {
    "site": "https://koreataxnlaw.com",
    "fixed_count": 1,
    "fixed": [
      {
        "id": 2677,
        "old": "Rethinking Unlock Your Korean Tax Refund: A Comprehensive Gu",
        "keyword_used": "Rethinking Korean Tax Refund A Comprehensive Guide for A",
        "new": "Rethinking Korean Tax Refund A Comprehensive Guide for A: A Closer Look at What Really Matters",
        "status": 200
      }
    ]
  },
  {
    "site": "https://koreacrypto365.com",
    "fixed_count": 1,
    "fixed": [
      {
        "id": 2327,
        "old": "OTC Crypto Desk Seoul Corporate: Busting Myths and Unveiling",
        "keyword_used": "OTC Crypto Desk Seoul Corporate Busting Myths and Unveiling",
        "new": "How OTC Crypto Desk Seoul Corporate Busting Myths and Unveiling Has Changed in 2026",
        "status": 200
      }
    ]
  },
  {
    "site": "https://krealestate365.com",
    "fixed_count": 0,
    "fixed": []
  },
  {
    "site": "https://ktech365.com",
    "fixed_count": 0,
    "fixed": []
  },
  {
    "site": "https://kskin365.com",
    "fixed_count": 6,
    "fixed": [
      {
        "id": 1652,
        "old": "Why Does Why Your Blackheads Won&#8217;t Wait: Unlocking the",
        "keyword_used": "Why Your Blackheads Won't Wait Korean Blackhead Removal",
        "new": "5 Mistakes People Make With Why Your Blackheads Won't Wait Korean Blackhead Removal",
        "status": 200
      },
      {
        "id": 1586,
        "old": "Propolis Skincare Korea: Top 7 Secrets to Unlocking Your Rad",
        "keyword_used": "Propolis Skincare Korea Your Radiant Glow",
        "new": "Propolis Skincare Korea Your Radiant Glow 101: What First-Timers Should Know",
        "status": 200
      },
      {
        "id": 1585,
        "old": "3 Mistakes People Make With Korean Sheet Masks Benefits: Unl",
        "keyword_used": "Korean Sheet Masks Benefits Glow",
        "new": "Before You Try Korean Sheet Masks Benefits Glow, Read This First",
        "status": 200
      },
      {
        "id": 1584,
        "old": "AHA BHA Exfoliants Korea: 7 Secrets to Unlocking Glass Skin ",
        "keyword_used": "AHA BHA Exfoliants Korea 7 Glass Skin",
        "new": "The Truth About AHA BHA Exfoliants Korea 7 Glass Skin That Most People Get Wrong",
        "status": 200
      },
      {
        "id": 1577,
        "old": "Why Does K-beauty Ingredients Guide: Unlock Your Glow with O",
        "keyword_used": "K-beauty Ingredients Guide Glow",
        "new": "K-beauty Ingredients Guide Glow Q&A: Answers From the Field",
        "status": 200
      },
      {
        "id": 1557,
        "old": "Why Does Unveiling the Secret: Your Ultimate K-Beauty Guide ",
        "keyword_used": "Soothing Sensitive Skin",
        "new": "How to Actually Handle Soothing Sensitive Skin: A Specialist's Guide",
        "status": 200
      }
    ]
  },
  {
    "site": "https://oliveyoungkorea.com",
    "fixed_count": 1,
    "fixed": [
      {
        "id": 70,
        "old": "Why Does Are You Overpaying? Unveiling the Truth About Olive",
        "keyword_used": "Are You Overpaying Unveiling the Truth About Olive Young",
        "new": "The Truth About Are You Overpaying Unveiling the Truth About Olive Young That Most People Get Wrong",
        "status": 200
      }
    ]
  },
  {
    "site": "https://kworld365.com",
    "fixed_count": 3,
    "fixed": [
      {
        "id": 139,
        "old": "How K-pop Lyrics Learning Korean: Unlocking the Language Thr",
        "keyword_used": "How K-pop Lyrics Learning Korean the Language Through Music",
        "new": "Why Does How K-pop Lyrics Learning Korean the Language Through Music Cause Problems? Experts Explain",
        "status": 200
      },
      {
        "id": 133,
        "old": "Unlocking the K-Pop World Plate-by-Plate: Essential Korean F",
        "keyword_used": "the K-Pop World Plate-by-Plate Essential Korean Food",
        "new": "How to Actually Handle the K-Pop World Plate-by-Plate Essential Korean Food: A Specialist's Guide",
        "status": 200
      },
      {
        "id": 127,
        "old": "Understanding the Pulse of K-Pop: A Deep Dive into # kworld3",
        "keyword_used": "Understanding the Pulse of K-Pop A Deep # kworld365.com 키워드",
        "new": "The Truth About Understanding the Pulse of K-Pop A Deep # kworld365.com 키워드 That Most People Get Wrong",
        "status": 200
      }
    ]
  },
  {
    "site": "https://k-trip365.com",
    "fixed_count": 2,
    "fixed": [
      {
        "id": 4385,
        "old": "Unlocking Seoul&#8217;s Secrets: Your Ultimate Seoul Hidden ",
        "keyword_used": "Seoul hidden spots guide",
        "new": "A Practical Look at Seoul hidden spots guide for International Patients",
        "status": 200
      },
      {
        "id": 3695,
        "old": "Don&#8217;t Wait to Unlock Your Ideal Korea Bundang Expat Fa",
        "keyword_used": "Don't Wait to Ideal Korea Bundang Expat Family Housing What",
        "new": "What Nobody Tells You About Don't Wait to Ideal Korea Bundang Expat Family Housing What",
        "status": 200
      }
    ]
  },
  {
    "site": "https://k-visa365.com",
    "fixed_count": 0,
    "fixed": []
  },
  {
    "site": "https://koreawedding365.com",
    "fixed_count": 0,
    "fixed": []
  },
  {
    "site": "https://kstudy365.com",
    "fixed_count": 4,
    "fixed": [
      {
        "id": 546,
        "old": "The Real Cost of Don&#8217;t Wait: Unlock Your Potential wit",
        "keyword_used": "The Real Cost of Don't Wait Potential with a Korea",
        "new": "The Real Cost of Don't Wait Potential with a Korea: A Closer Look at What Really Matters",
        "status": 200
      },
      {
        "id": 474,
        "old": "Korean Academic Calendar Schedule: Complete Guide to Unlock ",
        "keyword_used": "Korean Academic Calendar Schedule Complete Guide to Dream",
        "new": "The Truth About Korean Academic Calendar Schedule Complete Guide to Dream That Most People Get Wrong",
        "status": 200
      },
      {
        "id": 473,
        "old": "Professor Recommendation Letter Korea: Top 7 Secrets to Unlo",
        "keyword_used": "Professor Recommendation Letter Korea Dreams A Closer Look",
        "new": "Before You Try Professor Recommendation Letter Korea Dreams A Closer Look, Read This First",
        "status": 200
      },
      {
        "id": 468,
        "old": "5 Mistakes People Make With Korean Community College Guide: ",
        "keyword_used": "Korean Community College Guide Dream Career in",
        "new": "5 Things About Korean Community College Guide Dream Career in Your Doctor Wants You to Know",
        "status": 200
      }
    ]
  },
  {
    "site": "https://studyinkorea365.com",
    "fixed_count": 3,
    "fixed": [
      {
        "id": 2279,
        "old": "Unlock Your Future: Don&#8217;t Miss Out on Crucial Local Go",
        "keyword_used": "Future Don't Miss Out on Crucial Local Government Grants in",
        "new": "Future Don't Miss Out on Crucial Local Government Grants in Warning Signs You Should Never Ignore",
        "status": 200
      },
      {
        "id": 2249,
        "old": "How to Actually Handle Charting the Future: Unveiling the To",
        "keyword_used": "How to Actually Handle Charting the Future Unveiling the",
        "new": "The Real Cost of How to Actually Handle Charting the Future Unveiling the — What to Expect",
        "status": 200
      },
      {
        "id": 2242,
        "old": "Rethinking Unlock Your Dream: The Ultimate GKS Scholarship A",
        "keyword_used": "Rethinking Dream The Ultimate GKS Scholarship Application",
        "new": "Rethinking Dream The Ultimate GKS Scholarship Application Q&A: Answers From the Field",
        "status": 200
      }
    ]
  },
  {
    "site": "https://kieca-korea.org",
    "fixed_count": 0,
    "fixed": []
  },
  {
    "site": "https://ksa-korea.org",
    "fixed_count": 0,
    "fixed": []
  },
  {
    "site": "https://sis-korea.com",
    "fixed_count": 0,
    "fixed": []
  },
  {
    "site": "https://jobkorea365.com",
    "fixed_count": 0,
    "fixed": []
  },
  {
    "site": "https://jobinkorea365.com",
    "fixed_count": 3,
    "fixed": [
      {
        "id": 650,
        "old": "Unlocking Opportunities: My Essential Group Interview Korea ",
        "keyword_used": "group interview Korea tips",
        "new": "group interview Korea tips: Frequently Overlooked Facts",
        "status": 200
      },
      {
        "id": 649,
        "old": "Your Guide to Unlocking the Best Benefits Package Korea Comp",
        "keyword_used": "benefits package Korea company",
        "new": "benefits package Korea company: A Closer Look at What Really Matters",
        "status": 200
      },
      {
        "id": 268,
        "old": "Korea Job Fair Events 2026: Unlock Your Dream Career in Seou",
        "keyword_used": "Korea Job Fair Events 2026 Dream Career in Seoul",
        "new": "Korea Job Fair Events 2026 Dream Career in Seoul Warning Signs You Should Never Ignore",
        "status": 200
      }
    ]
  },
  {
    "site": "https://jobkoreaglobal.com",
    "fixed_count": 0,
    "fixed": []
  },
  {
    "site": "https://korea365.org",
    "fixed_count": 3,
    "fixed": [
      {
        "id": 1966,
        "old": "Unlocking Korea: Essential Learning Korean Tips for Expats",
        "keyword_used": "learning Korean tips expat",
        "new": "learning Korean tips expat Warning Signs You Should Never Ignore",
        "status": 200
      },
      {
        "id": 1965,
        "old": "Chuseok Celebration Guide: Unveiling Korea&#8217;s Harvest M",
        "keyword_used": "Chuseok celebration guide",
        "new": "Chuseok celebration guide: Frequently Overlooked Facts",
        "status": 200
      },
      {
        "id": 1638,
        "old": "Stop Missing Out: Unlocking the Best K-drama Filming Locatio",
        "keyword_used": "K-drama filming location Seoul",
        "new": "The Truth About K-drama filming location Seoul That Most People Get Wrong",
        "status": 200
      }
    ]
  },
  {
    "site": "https://koreanews365.com",
    "fixed_count": 0,
    "fixed": []
  },
  {
    "site": "https://theseouljournal.com",
    "fixed_count": 0,
    "fixed": []
  }
]