{
  "categories": [
    {
      "id": 401,
      "name": "Etc",
      "count": 0
    },
    {
      "id": 398,
      "name": "Jobs",
      "count": 32
    },
    {
      "id": 399,
      "name": "Salaries",
      "count": 2
    },
    {
      "id": 1,
      "name": "Uncategorized",
      "count": 3
    },
    {
      "id": 400,
      "name": "Work Visa",
      "count": 5
    }
  ],
  "recent_posts": [
    {
      "id": 726,
      "date": "2026-07-13T17:42:06",
      "title": "visa status check Korea work: Frequently Overlooked Facts",
      "img_count": 3
    },
    {
      "id": 724,
      "date": "2026-07-13T07:20:35",
      "title": "6 Mistakes People Make With E-7 visa to F-2 visa",
      "img_count": 3
    },
    {
      "id": 646,
      "date": "2026-07-12T23:55:29",
      "title": "The Truth About E-7 Visa Sponsored Job Korea That Most People Get Wrong",
      "img_count": 3
    },
    {
      "id": 645,
      "date": "2026-07-12T19:17:37",
      "title": "How to Actually Fix Your E-7 Visa Job Change Strategy: A Specialist&#8217;s Guide",
      "img_count": 3
    },
    {
      "id": 644,
      "date": "2026-07-12T07:04:15",
      "title": "Mastering the Bonus Culture in Korean Companies: An Insider&#8217;s Playbook for Job Seekers",
      "img_count": 3
    }
  ]
}