[
  {
    "site": "https://oliveyoungkorea.com",
    "changed": 24,
    "total": 25,
    "entries": [
      {
        "id": 613,
        "title": "Beauty of Joseon review: Frequently Over",
        "new_cat_id": 384,
        "status": 200
      },
      {
        "id": 612,
        "title": "Before You Try Korean toner pads review,",
        "new_cat_id": 363,
        "status": 200
      },
      {
        "id": 611,
        "title": "Korean sunscreen no white cast Explained",
        "new_cat_id": 363,
        "status": 200
      },
      {
        "id": 467,
        "title": "How to Actually Handle Anua heartleaf to",
        "new_cat_id": 363,
        "status": 200
      },
      {
        "id": 465,
        "title": "Study Reveals: 8 in 10 People Misunderst",
        "new_cat_id": 363,
        "status": 200
      },
      {
        "id": 389,
        "title": "How Olive Young supplements Korea Has Ch",
        "new_cat_id": 363,
        "status": 200
      },
      {
        "id": 388,
        "title": "7 Things About Mediheal mask review Your",
        "new_cat_id": 363,
        "status": 200
      },
      {
        "id": 387,
        "title": "Korean inner beauty drink Q&#038;A: Answ",
        "new_cat_id": 381,
        "status": 200
      },
      {
        "id": 386,
        "title": "5 Mistakes People Make With Korean inner",
        "new_cat_id": 363,
        "status": 200
      },
      {
        "id": 385,
        "title": "Behind the Scenes: What Korean inner bea",
        "new_cat_id": 381,
        "status": 200
      },
      {
        "id": 384,
        "title": "7 Mistakes People Make With Korean immun",
        "new_cat_id": 384,
        "status": 200
      },
      {
        "id": 381,
        "title": "Round Lab toner review: Frequently Overl",
        "new_cat_id": 384,
        "status": 200
      },
      {
        "id": 380,
        "title": "Anua heartleaf toner review Q&#038;A: An",
        "new_cat_id": 381,
        "status": 200
      },
      {
        "id": 379,
        "title": "How Skin1004 ampoule review Has Changed ",
        "new_cat_id": 363,
        "status": 200
      },
      {
        "id": 377,
        "title": "Behind the Scenes: What Korean serum bes",
        "new_cat_id": 381,
        "status": 200
      },
      {
        "id": 373,
        "title": "Is Olive Young eye cream Really Worth It",
        "new_cat_id": 381,
        "status": 200
      },
      {
        "id": 339,
        "title": "What Nobody Tells You About Korean detox",
        "new_cat_id": 384,
        "status": 200
      },
      {
        "id": 313,
        "title": "Skin1004 ampoule review: A Closer Look a",
        "new_cat_id": 363,
        "status": 200
      },
      {
        "id": 251,
        "title": "8 Things About Purito centella serum rev",
        "new_cat_id": 384,
        "status": 200
      },
      {
        "id": 200,
        "title": "Study Reveals: 4 in 10 People Misunderst",
        "new_cat_id": 363,
        "status": 200
      },
      {
        "id": 196,
        "title": "Heimish clean balm review Explained in P",
        "new_cat_id": 363,
        "status": 200
      },
      {
        "id": 145,
        "title": "bbia eyeliner review 101: What First-Tim",
        "new_cat_id": 381,
        "status": 200
      },
      {
        "id": 144,
        "title": "Rethinking Romand lip tint review: A Fre",
        "new_cat_id": 363,
        "status": 200
      },
      {
        "id": 143,
        "title": "5 Mistakes People Make With bbia eyeline",
        "new_cat_id": 381,
        "status": 200
      }
    ]
  },
  {
    "site": "https://theseouljournal.com",
    "changed": 23,
    "total": 25,
    "entries": [
      {
        "id": 3450,
        "title": "Is 14th Korean oil tanker successfully t",
        "new_cat_id": 573,
        "status": 200
      },
      {
        "id": 3449,
        "title": "How to Actually Handle Hopes for US-Iran",
        "new_cat_id": 19,
        "status": 200
      },
      {
        "id": 3448,
        "title": "Is How RESCENE&#8217;s real story broke ",
        "new_cat_id": 573,
        "status": 200
      },
      {
        "id": 3447,
        "title": "Rethinking Outgoing Irish ambassador ref",
        "new_cat_id": 20,
        "status": 200
      },
      {
        "id": 3446,
        "title": "4 Mistakes People Make With From paralys",
        "new_cat_id": 19,
        "status": 200
      },
      {
        "id": 3445,
        "title": "How RESCENE&#8217;s real story broke thr",
        "new_cat_id": 573,
        "status": 200
      },
      {
        "id": 3238,
        "title": "K-beauty shopping diversifies beyond Oli",
        "new_cat_id": 20,
        "status": 200
      },
      {
        "id": 3119,
        "title": "Cost of Living in Seoul 2026: A Closer L",
        "new_cat_id": 573,
        "status": 200
      },
      {
        "id": 3117,
        "title": "The transition to senior living is best ",
        "new_cat_id": 19,
        "status": 200
      },
      {
        "id": 3116,
        "title": "Before You Try Inside Korea&#8217;s larg",
        "new_cat_id": 19,
        "status": 200
      },
      {
        "id": 3115,
        "title": "What Nobody Tells You About Inside a Kor",
        "new_cat_id": 19,
        "status": 200
      },
      {
        "id": 3113,
        "title": "The Real Cost of China celebrates 65th a",
        "new_cat_id": 20,
        "status": 200
      },
      {
        "id": 3112,
        "title": "Study Reveals: 4 in 10 People Misunderst",
        "new_cat_id": 573,
        "status": 200
      },
      {
        "id": 3111,
        "title": "Why Does Busan&#8217;s oldest industrial",
        "new_cat_id": 19,
        "status": 200
      },
      {
        "id": 3110,
        "title": "What Nobody Tells You About AI fortune-t",
        "new_cat_id": 573,
        "status": 200
      },
      {
        "id": 3108,
        "title": "[K-LIT REVIEW] &#8216;Mrs. Shim is a Kil",
        "new_cat_id": 573,
        "status": 200
      },
      {
        "id": 3103,
        "title": "Debunking Common Myths About Gyeonggi Pr",
        "new_cat_id": 20,
        "status": 200
      },
      {
        "id": 3100,
        "title": "Can&#8217;t stop snacking? Eat this firs",
        "new_cat_id": 573,
        "status": 200
      },
      {
        "id": 3098,
        "title": "3 Things About Top diplomats of Seoul Yo",
        "new_cat_id": 573,
        "status": 200
      },
      {
        "id": 3055,
        "title": "The Real Cost of Cafes and Co-working Sp",
        "new_cat_id": 573,
        "status": 200
      },
      {
        "id": 3005,
        "title": "Love bread? Add one more thing to every ",
        "new_cat_id": 1,
        "status": 200
      },
      {
        "id": 2947,
        "title": "The Real Cost of Creating blessings — Wh",
        "new_cat_id": 20,
        "status": 200
      },
      {
        "id": 2870,
        "title": "Why Does Korea&#8217;s World Cup elimina",
        "new_cat_id": 19,
        "status": 200
      }
    ]
  },
  {
    "site": "https://krealestate365.com",
    "changed": 23,
    "total": 25,
    "entries": [
      {
        "id": 401,
        "title": "jeonse system Korea foreigner, 당신이 아는 것과",
        "new_cat_id": 262,
        "status": 200
      },
      {
        "id": 400,
        "title": "industrial property Korea, 제대로 대처하는 법 — ",
        "new_cat_id": 262,
        "status": 200
      },
      {
        "id": 399,
        "title": "foreigner land purchase Korea에 대한 흔한 오해 ",
        "new_cat_id": 262,
        "status": 200
      },
      {
        "id": 317,
        "title": "capital gains tax real estate Korea, 정말 ",
        "new_cat_id": 261,
        "status": 200
      },
      {
        "id": 314,
        "title": "business location Korea foreigner의 진짜 비용",
        "new_cat_id": 262,
        "status": 200
      },
      {
        "id": 257,
        "title": "real estate registration tax Korea, 정말 효",
        "new_cat_id": 261,
        "status": 200
      },
      {
        "id": 256,
        "title": "절대 놓치면 안 되는 restaurant lease Korea forei",
        "new_cat_id": 261,
        "status": 200
      },
      {
        "id": 255,
        "title": "foreigner land purchase Korea에 대한 흔한 오해,",
        "new_cat_id": 262,
        "status": 200
      },
      {
        "id": 252,
        "title": "REIT investment Korea foreigner에 대해 자주 놓",
        "new_cat_id": 261,
        "status": 200
      },
      {
        "id": 251,
        "title": "acquisition tax Korea foreigner, 정말 효과가 ",
        "new_cat_id": 261,
        "status": 200
      },
      {
        "id": 250,
        "title": "property inheritance Korea foreigner 궁금증",
        "new_cat_id": 261,
        "status": 200
      },
      {
        "id": 248,
        "title": "HUG jeonse insurance Korea 시작 전에 꼭 읽어야 할",
        "new_cat_id": 263,
        "status": 200
      },
      {
        "id": 245,
        "title": "외국인을 위한 property tax Korea foreigner 실전 ",
        "new_cat_id": 261,
        "status": 200
      },
      {
        "id": 243,
        "title": "foreigner land purchase Korea 시작 전에 꼭 읽어",
        "new_cat_id": 262,
        "status": 200
      },
      {
        "id": 236,
        "title": "real estate fund Korea foreigner 입문 — 처음",
        "new_cat_id": 262,
        "status": 200
      },
      {
        "id": 186,
        "title": "acquisition tax Korea foreigner, 왜 이런 문제",
        "new_cat_id": 261,
        "status": 200
      },
      {
        "id": 184,
        "title": "office rent Seoul foreigner, 정말 중요한 건 따로",
        "new_cat_id": 261,
        "status": 200
      },
      {
        "id": 171,
        "title": "REIT investment Korea foreigner에 대해 의사가 ",
        "new_cat_id": 261,
        "status": 200
      },
      {
        "id": 107,
        "title": "Korea real estate transaction process에 대",
        "new_cat_id": 263,
        "status": 200
      },
      {
        "id": 93,
        "title": "2026년, where to stay in Seoul for a mont",
        "new_cat_id": 261,
        "status": 200
      },
      {
        "id": 65,
        "title": "how to pay rent in Korea foreigner에 대해 자",
        "new_cat_id": 261,
        "status": 200
      },
      {
        "id": 60,
        "title": "short term housing Seoul expat 입문 — 처음이라",
        "new_cat_id": 261,
        "status": 200
      },
      {
        "id": 31,
        "title": "Korea jeonse explained for foreigners, 정",
        "new_cat_id": 262,
        "status": 200
      }
    ]
  },
  {
    "site": "https://koreamedicaltour.com",
    "changed": 18,
    "total": 25,
    "entries": [
      {
        "id": 1272,
        "title": "Rethinking Korea medical tour package of",
        "new_cat_id": 686,
        "status": 200
      },
      {
        "id": 1146,
        "title": "A Practical Look at medical tourism supp",
        "new_cat_id": 687,
        "status": 200
      },
      {
        "id": 1127,
        "title": "The Truth About botox filler price Korea",
        "new_cat_id": 686,
        "status": 200
      },
      {
        "id": 1126,
        "title": "Is IVF cost Korea foreigner Really Worth",
        "new_cat_id": 688,
        "status": 200
      },
      {
        "id": 999,
        "title": "How to Actually Navigate Seoul Hospital ",
        "new_cat_id": 688,
        "status": 200
      },
      {
        "id": 998,
        "title": "How to Actually Navigate KHIDI Medical T",
        "new_cat_id": 686,
        "status": 200
      },
      {
        "id": 985,
        "title": "Navigating Your Facial Contouring Journe",
        "new_cat_id": 686,
        "status": 200
      },
      {
        "id": 984,
        "title": "Busan Medical Tourism Benefits: A Closer",
        "new_cat_id": 686,
        "status": 200
      },
      {
        "id": 983,
        "title": "Navigating World-Class Healthcare: The P",
        "new_cat_id": 687,
        "status": 200
      },
      {
        "id": 978,
        "title": "Busan medical tourism benefits 101: What",
        "new_cat_id": 686,
        "status": 200
      },
      {
        "id": 977,
        "title": "Behind the Scenes: What Busan medical to",
        "new_cat_id": 687,
        "status": 200
      },
      {
        "id": 975,
        "title": "Daegu plastic surgery subsidy: Is it tru",
        "new_cat_id": 686,
        "status": 200
      },
      {
        "id": 972,
        "title": "cancer treatment cost Korea vs What You ",
        "new_cat_id": 687,
        "status": 200
      },
      {
        "id": 951,
        "title": "The truth About medical visa Korea cost ",
        "new_cat_id": 688,
        "status": 200
      },
      {
        "id": 901,
        "title": "What a facial contouring Korea review Ex",
        "new_cat_id": 687,
        "status": 200
      },
      {
        "id": 899,
        "title": "The Real Reason Anti Aging Treatment Kor",
        "new_cat_id": 687,
        "status": 200
      },
      {
        "id": 871,
        "title": "What 3 Months of laser skin treatment Se",
        "new_cat_id": 687,
        "status": 200
      },
      {
        "id": 807,
        "title": "Regenerative Medicine: Why Ignoring stem",
        "new_cat_id": 686,
        "status": 200
      }
    ]
  },
  {
    "site": "https://koreacrypto365.com",
    "changed": 18,
    "total": 25,
    "entries": [
      {
        "id": 2936,
        "title": "What Nobody Tells You About Upbit regist",
        "new_cat_id": 482,
        "status": 200
      },
      {
        "id": 2935,
        "title": "Before You Try Korea crypto AML rules, R",
        "new_cat_id": 481,
        "status": 200
      },
      {
        "id": 2934,
        "title": "What Nobody Tells You About Coinone sign",
        "new_cat_id": 481,
        "status": 200
      },
      {
        "id": 2782,
        "title": "The Real Cost of Upbit English guide for",
        "new_cat_id": 480,
        "status": 200
      },
      {
        "id": 2772,
        "title": "Debunking Common Myths About crypto tax ",
        "new_cat_id": 481,
        "status": 200
      },
      {
        "id": 2688,
        "title": "The Real Cost of crypto trading strategy",
        "new_cat_id": 481,
        "status": 200
      },
      {
        "id": 2687,
        "title": "How to Actually Handle how foreigner buy",
        "new_cat_id": 481,
        "status": 200
      },
      {
        "id": 2686,
        "title": "Korean exchange real name verification Q",
        "new_cat_id": 480,
        "status": 200
      },
      {
        "id": 2684,
        "title": "What Nobody Tells You About crypto tradi",
        "new_cat_id": 481,
        "status": 200
      },
      {
        "id": 2683,
        "title": "Bithumb account foreigner: Frequently Ov",
        "new_cat_id": 481,
        "status": 200
      },
      {
        "id": 2682,
        "title": "What Nobody Tells You About FSC crypto p",
        "new_cat_id": 482,
        "status": 200
      },
      {
        "id": 2677,
        "title": "8 Things About Upbit registration foreig",
        "new_cat_id": 482,
        "status": 200
      },
      {
        "id": 2676,
        "title": "Study Reveals: 9 in 10 People Misunderst",
        "new_cat_id": 481,
        "status": 200
      },
      {
        "id": 2606,
        "title": "How DeFi participation Korea foreigner H",
        "new_cat_id": 480,
        "status": 200
      },
      {
        "id": 2604,
        "title": "Coinone signup foreigner Korea 101: What",
        "new_cat_id": 481,
        "status": 200
      },
      {
        "id": 2577,
        "title": "A Practical Look at DAO legal status Kor",
        "new_cat_id": 482,
        "status": 200
      },
      {
        "id": 2527,
        "title": "Study Reveals: 5 in 10 People Misunderst",
        "new_cat_id": 481,
        "status": 200
      },
      {
        "id": 2513,
        "title": "How Web3 gaming Korea trend Has Changed ",
        "new_cat_id": 480,
        "status": 200
      }
    ]
  },
  {
    "site": "https://korea365.org",
    "changed": 20,
    "total": 25,
    "entries": [
      {
        "id": 2240,
        "title": "What Nobody Tells You About Korean tradi",
        "new_cat_id": 743,
        "status": 200
      },
      {
        "id": 2239,
        "title": "Korean martial arts Taekwondo: Frequentl",
        "new_cat_id": 560,
        "status": 200
      },
      {
        "id": 2238,
        "title": "traditional Korean market 101: What Firs",
        "new_cat_id": 560,
        "status": 200
      },
      {
        "id": 2237,
        "title": "3 Mistakes People Make With Seollal new ",
        "new_cat_id": 560,
        "status": 200
      },
      {
        "id": 2236,
        "title": "community for expat Seoul vs What You Th",
        "new_cat_id": 560,
        "status": 200
      },
      {
        "id": 2108,
        "title": "4 Mistakes People Make With learning Kor",
        "new_cat_id": 737,
        "status": 200
      },
      {
        "id": 2107,
        "title": "Korean calligraphy experience vs What Yo",
        "new_cat_id": 737,
        "status": 200
      },
      {
        "id": 1975,
        "title": "What Makes Korean Street Food So Irresis",
        "new_cat_id": 560,
        "status": 200
      },
      {
        "id": 1974,
        "title": "The Truth About Korean Recycling Rules E",
        "new_cat_id": 737,
        "status": 200
      },
      {
        "id": 1973,
        "title": "7 Things About Taekwondo Your Doctor Wan",
        "new_cat_id": 560,
        "status": 200
      },
      {
        "id": 1971,
        "title": "The Unexpected Culinary Delights of Kore",
        "new_cat_id": 560,
        "status": 200
      },
      {
        "id": 1969,
        "title": "Unraveling the Intricacies of Recycling ",
        "new_cat_id": 743,
        "status": 200
      },
      {
        "id": 1967,
        "title": "The Soulful Slurp: Unpacking Korean Rame",
        "new_cat_id": 560,
        "status": 200
      },
      {
        "id": 1966,
        "title": "learning Korean tips expat Warning Signs",
        "new_cat_id": 560,
        "status": 200
      },
      {
        "id": 1965,
        "title": "Chuseok celebration guide: Frequently Ov",
        "new_cat_id": 743,
        "status": 200
      },
      {
        "id": 1964,
        "title": "Jeju Food Specialty Guide: A Culinary Jo",
        "new_cat_id": 560,
        "status": 200
      },
      {
        "id": 1859,
        "title": "I Scored 80% Off My Insadong Shopping Gu",
        "new_cat_id": 737,
        "status": 200
      },
      {
        "id": 1817,
        "title": "Stop Wasting Money on Hongdae nightlife ",
        "new_cat_id": 737,
        "status": 200
      },
      {
        "id": 1805,
        "title": "What 3 Months of temple stay experience ",
        "new_cat_id": 560,
        "status": 200
      },
      {
        "id": 1690,
        "title": "Are You Ready for the Ultimate Jimjilban",
        "new_cat_id": 560,
        "status": 200
      }
    ]
  }
]